{
  "lenses": [
    {
      "id": "angenieux-optimo-15-40",
      "lensType": "cine",
      "manufacturerUrl": "https://www.angenieux.com/cinema/optimo",
      "weightG": 1920,
      "lengthMm": 235,
      "frontDiameterMm": 114,
      "closeFocusM": 0.61,
      "introductionYear": null,
      "imageCircleMm": 31.4,
      "opticalElements": "unknown",
      "filterType": "matte_box",
      "filterThreadMm": "none",
      "isParfocal": true,
      "hasFocusBreathing": "none",
      "hasFrontRotation": null,
      "focusRingRotationDeg": 320,
      "gearPitch": 0.8,
      "sources": {
        "imageCircleMm": "Angénieux S35 Optimo product specifications",
        "weightG": "Duclos Lenses spec database",
        "lengthMm": "Duclos Lenses spec database",
        "frontDiameterMm": "Duclos Lenses spec database",
        "closeFocusM": "Duclos Lenses spec database",
        "filterType": "114mm front barrel confirmed, no filter thread found — matte_box classification consistent with Optimo Style 16-40/30-76",
        "filterThreadMm": "cinevisuals.com; bhphotovideo.com; ottonemenz.com — 114mm front, geen thread",
        "focusRingRotationDeg": "Preston FIZ motor database",
        "gearPitch": "Standard M0.8 cinema pitch",
        "isParfocal": "Angénieux Classic Optimo documentation -- angenieux.com (Tier 1)",
        "hasFocusBreathing": "Angénieux Classic Optimo documentation -- angenieux.com (Tier 1)"
      },
      "webSources": [
        "https://www.angenieux.com/cinema/optimo"
      ]
    },
    {
      "id": "angenieux-optimo-17-80",
      "lensType": "cine",
      "manufacturerUrl": "https://www.angenieux.com/cinema/optimo",
      "weightG": 5500,
      "lengthMm": 325,
      "frontDiameterMm": 136,
      "closeFocusM": 0.61,
      "introductionYear": null,
      "imageCircleMm": 31.4,
      "opticalElements": "unknown",
      "filterType": "matte_box",
      "filterThreadMm": "none",
      "isParfocal": true,
      "hasFocusBreathing": "none",
      "hasFrontRotation": null,
      "focusRingRotationDeg": 327,
      "gearPitch": 0.8,
      "sources": {
        "imageCircleMm": "Angénieux S35 Optimo product specifications",
        "weightG": "Duclos Lenses spec database",
        "lengthMm": "Duclos Lenses spec database",
        "frontDiameterMm": "Duclos Lenses spec database",
        "closeFocusM": "Duclos Lenses spec database",
        "filterThreadMm": "cinerent.net; cinetecnico.com — 136mm front, geen thread",
        "focusRingRotationDeg": "Preston FIZ motor database",
        "gearPitch": "Standard M0.8 cinema pitch",
        "isParfocal": "Angénieux Reference Manual -- angenieux.com (Tier 1)",
        "hasFocusBreathing": "Angénieux Reference Manual -- angenieux.com (Tier 1)"
      },
      "webSources": [
        "https://www.angenieux.com/cinema/optimo"
      ]
    },
    {
      "id": "angenieux-optimo-19-5-94",
      "lensType": "cine",
      "manufacturerUrl": "https://www.angenieux.com/cinema/optimo",
      "weightG": 5600,
      "lengthMm": 335,
      "frontDiameterMm": 136,
      "closeFocusM": 0.62,
      "introductionYear": null,
      "imageCircleMm": 31.4,
      "opticalElements": "unknown",
      "filterType": "matte_box",
      "filterThreadMm": "none",
      "isParfocal": true,
      "hasFocusBreathing": "none",
      "hasFrontRotation": false,
      "focusRingRotationDeg": 320,
      "gearPitch": 0.8,
      "sources": {
        "imageCircleMm": "Angénieux S35 Optimo product specifications",
        "weightG": "Duclos Lenses spec database",
        "lengthMm": "Duclos Lenses spec database",
        "frontDiameterMm": "Duclos Lenses spec database",
        "closeFocusM": "Duclos Lenses spec database",
        "filterThreadMm": "bhphotovideo.com; ottonemenz.com — 136mm front, geen thread",
        "hasFrontRotation": "Angénieux documentation: internal focus confirmed",
        "gearPitch": "Standard M0.8 cinema pitch",
        "focusRingRotationDeg": "Filmtools product page (Tier 3): \"focus ring with scale rotation of 320 degrees.\" Multiple rental house and dealer sources consistent.",
        "isParfocal": "Angénieux Large Scale Zoom catalog -- angenieux.com (Tier 1)",
        "hasFocusBreathing": "Angénieux Large Scale Zoom catalog -- angenieux.com (Tier 1)"
      },
      "webSources": [
        "https://www.angenieux.com/cinema/optimo"
      ]
    },
    {
      "id": "angenieux-optimo-24-290",
      "lensType": "cine",
      "manufacturerUrl": "https://www.angenieux.com/cinema/optimo",
      "weightG": 11000,
      "lengthMm": 440,
      "frontDiameterMm": 162,
      "closeFocusM": 1.22,
      "introductionYear": null,
      "imageCircleMm": 31.4,
      "opticalElements": "unknown",
      "filterType": "matte_box",
      "filterThreadMm": "none",
      "isParfocal": true,
      "hasFocusBreathing": "none",
      "hasFrontRotation": false,
      "focusRingRotationDeg": 327,
      "gearPitch": 0.8,
      "sources": {
        "imageCircleMm": "Angénieux S35 Optimo product specifications",
        "weightG": "Duclos Lenses spec database",
        "lengthMm": "Duclos Lenses spec database",
        "frontDiameterMm": "Duclos Lenses spec database",
        "closeFocusM": "Duclos Lenses spec database",
        "filterThreadMm": "bhphotovideo.com; vmi.tv — 162mm front, geen thread",
        "hasFrontRotation": "Angénieux documentation: internal focus confirmed",
        "focusRingRotationDeg": "Preston FIZ motor database",
        "gearPitch": "Standard M0.8 cinema pitch",
        "isParfocal": "Angénieux Large Scale Zoom catalog -- angenieux.com (Tier 1)",
        "hasFocusBreathing": "Angénieux Large Scale Zoom catalog -- angenieux.com (Tier 1)"
      },
      "webSources": [
        "https://www.angenieux.com/cinema/optimo"
      ]
    },
    {
      "id": "angenieux-optimo-28-340",
      "lensType": "cine",
      "manufacturerUrl": "https://www.angenieux.com/cinema/optimo",
      "weightG": 11100,
      "lengthMm": 454,
      "frontDiameterMm": 162,
      "closeFocusM": 1.23,
      "introductionYear": null,
      "imageCircleMm": 31.4,
      "opticalElements": "unknown",
      "filterType": "matte_box",
      "filterThreadMm": "none",
      "isParfocal": true,
      "hasFocusBreathing": "none",
      "hasFrontRotation": null,
      "focusRingRotationDeg": 327,
      "gearPitch": 0.8,
      "sources": {
        "imageCircleMm": "Angénieux S35 Optimo product specifications",
        "weightG": "Duclos Lenses spec database",
        "lengthMm": "Duclos Lenses spec database",
        "frontDiameterMm": "Duclos Lenses spec database",
        "closeFocusM": "Duclos Lenses spec database",
        "filterThreadMm": "bhphotovideo.com; angenieux.com 28-340 PDF — 162mm front, geen thread",
        "gearPitch": "Standard M0.8 cinema pitch",
        "focusRingRotationDeg": "MP&E Cameras + Greenwood Cinema (Tier 3): \"327° focus rotation.\" Multiple sources consistent.",
        "isParfocal": "Angénieux Large Scale Zoom catalog -- angenieux.com (Tier 1)",
        "hasFocusBreathing": "Angénieux Large Scale Zoom catalog -- angenieux.com (Tier 1)"
      },
      "webSources": [
        "https://www.angenieux.com/cinema/optimo"
      ]
    },
    {
      "id": "angenieux-optimo-28-76",
      "lensType": "cine",
      "manufacturerUrl": "https://www.angenieux.com/cinema/optimo",
      "weightG": 1920,
      "lengthMm": 247,
      "frontDiameterMm": 114,
      "closeFocusM": 0.61,
      "introductionYear": null,
      "imageCircleMm": 31.4,
      "opticalElements": "unknown",
      "filterType": "matte_box",
      "filterThreadMm": "none",
      "isParfocal": true,
      "hasFocusBreathing": "none",
      "hasFrontRotation": null,
      "focusRingRotationDeg": 320,
      "gearPitch": 0.8,
      "sources": {
        "imageCircleMm": "Angénieux S35 Optimo product specifications",
        "weightG": "Duclos Lenses spec database",
        "lengthMm": "Duclos Lenses spec database",
        "frontDiameterMm": "Duclos Lenses spec database",
        "closeFocusM": "Duclos Lenses spec database",
        "filterType": "114mm front barrel confirmed, no filter thread found — matte_box classification consistent with Optimo Style 16-40/30-76",
        "filterThreadMm": "cinevisuals.com; bhphotovideo.com — 114mm front, geen thread",
        "focusRingRotationDeg": "Preston FIZ motor database",
        "gearPitch": "Standard M0.8 cinema pitch",
        "isParfocal": "Angénieux Classic Optimo documentation -- angenieux.com (Tier 1)",
        "hasFocusBreathing": "Angénieux Classic Optimo documentation -- angenieux.com (Tier 1)"
      },
      "webSources": [
        "https://www.angenieux.com/cinema/optimo"
      ]
    },
    {
      "id": "angenieux-optimo-45-120",
      "lensType": "cine",
      "manufacturerUrl": "https://www.angenieux.com/cinema/optimo",
      "weightG": 1950,
      "lengthMm": 190,
      "frontDiameterMm": 114,
      "closeFocusM": 0.61,
      "introductionYear": null,
      "imageCircleMm": 31.4,
      "opticalElements": "unknown",
      "filterType": "matte_box",
      "filterThreadMm": "none",
      "isParfocal": true,
      "hasFocusBreathing": "none",
      "hasFrontRotation": null,
      "focusRingRotationDeg": 320,
      "gearPitch": 0.8,
      "sources": {
        "imageCircleMm": "Angénieux S35 Optimo product specifications",
        "weightG": "Duclos Lenses spec database",
        "lengthMm": "Duclos Lenses spec database",
        "frontDiameterMm": "Duclos Lenses spec database",
        "closeFocusM": "Duclos Lenses spec database",
        "filterType": "114mm front barrel confirmed, no filter thread found — matte_box classification consistent with Optimo Style 16-40/30-76",
        "filterThreadMm": "cinevisuals.com — 114mm front, geen thread",
        "focusRingRotationDeg": "Preston FIZ motor database",
        "gearPitch": "Standard M0.8 cinema pitch",
        "isParfocal": "Angénieux Classic Optimo documentation -- angenieux.com (Tier 1)",
        "hasFocusBreathing": "Angénieux Classic Optimo documentation -- angenieux.com (Tier 1)"
      },
      "webSources": [
        "https://www.angenieux.com/cinema/optimo"
      ]
    },
    {
      "id": "angenieux-optimo-dp-16-42mm-t2-8",
      "lensType": "cine",
      "manufacturerUrl": "https://www.angenieux.com/cinema-lenses/optimo-dp/",
      "weightG": 1920,
      "lengthMm": 190.0,
      "frontDiameterMm": 114,
      "closeFocusM": 0.61,
      "introductionYear": null,
      "imageCircleMm": 31.1,
      "opticalElements": null,
      "filterType": "matte_box",
      "filterThreadMm": "none",
      "isParfocal": false,
      "hasFocusBreathing": "none",
      "hasFrontRotation": null,
      "focusRingRotationDeg": 320,
      "gearPitch": 0.8,
      "sources": {
        "manufacturerUrl": "angenieux.com/cinema-lenses/optimo-dp/ (tier-1; page now returns 404; lens discontinued)",
        "weightG": "ManualsLib Optimo DP 16-42 OEM manual: 1.92 kg / 4.2 lbs = 1920g. ManualsLib Angénieux Optimo DP OEM manual (tier-1) + VMI rental hire page / ovide.com (tier-2)",
        "lengthMm": "ManualsLib Optimo DP 16-42 OEM manual: 190mm. ManualsLib Angénieux Optimo DP OEM manual (tier-1) + VMI rental hire page / ovide.com (tier-2)",
        "frontDiameterMm": "VMI rental hire page: 114mm front diameter. ManualsLib Angénieux Optimo DP OEM manual (tier-1) + VMI rental hire page / ovide.com (tier-2)",
        "closeFocusM": "ManualsLib / VMI rental: 0.61m / 2 ft. ManualsLib Angénieux Optimo DP OEM manual (tier-1) + VMI rental hire page / ovide.com (tier-2)",
        "introductionYear": "Not found in searchable press archives across 6 tiers",
        "imageCircleMm": "VMI rental: 31.1mm Super 35 / 5K diagonal. ManualsLib Angénieux Optimo DP OEM manual (tier-1) + VMI rental hire page / ovide.com (tier-2)",
        "opticalElements": "Not published in Optimo DP documentation",
        "filterType": "ManualsLib OEM manual: internal filter slot only; no front filter thread; filter type uncertain — null",
        "filterThreadMm": "filterType null; internal slot only, no thread size applicable",
        "isParfocal": "Parfocal not explicitly claimed for Optimo DP 16-42mm; POS-D11 applied",
        "hasFocusBreathing": "hhf-old.handheldfilms.com; bhphotovideo.com; fjsinternational.com — Zero Breathing and Ramping",
        "hasFrontRotation": "Not stated in accessible documentation",
        "focusRingRotationDeg": "ManualsLib Optimo DP 16-42 OEM manual: 320 degrees. ManualsLib Angénieux Optimo DP OEM manual (tier-1) + VMI rental hire page / ovide.com (tier-2)",
        "gearPitch": "ManualsLib OEM manual: legacy pitch-32 system (25.4/32 = 0.794mm module ≈ 0.8mm) (tier-1)"
      },
      "webSources": [
        "https://www.angenieux.com/cinema-lenses/optimo-dp/"
      ]
    },
    {
      "id": "angenieux-optimo-dp-30-80mm-t2-8",
      "lensType": "cine",
      "manufacturerUrl": "https://www.angenieux.com/cinema-lenses/optimo-dp/",
      "weightG": 1900,
      "lengthMm": 186.0,
      "frontDiameterMm": 114,
      "closeFocusM": 0.61,
      "introductionYear": null,
      "imageCircleMm": 31.4,
      "opticalElements": null,
      "filterType": "matte_box",
      "filterThreadMm": "none",
      "isParfocal": false,
      "hasFocusBreathing": "none",
      "hasFrontRotation": null,
      "focusRingRotationDeg": 320,
      "gearPitch": 0.8,
      "sources": {
        "manufacturerUrl": "angenieux.com/cinema-lenses/optimo-dp/ (tier-1; page now returns 404; lens discontinued)",
        "weightG": "VMI rental hire page: ~1.9 kg = 1900g. ManualsLib Angénieux Optimo DP OEM manual (tier-1) + VMI rental hire page / ovide.com (tier-2)",
        "lengthMm": "VMI rental hire page: 186mm. ManualsLib Angénieux Optimo DP OEM manual (tier-1) + VMI rental hire page / ovide.com (tier-2)",
        "frontDiameterMm": "VMI rental hire page: 114mm front diameter. ManualsLib Angénieux Optimo DP OEM manual (tier-1) + VMI rental hire page / ovide.com (tier-2)",
        "closeFocusM": "VMI rental / ovide.com: 0.61m / 2 ft. ManualsLib Angénieux Optimo DP OEM manual (tier-1) + VMI rental hire page / ovide.com (tier-2)",
        "introductionYear": "Not found in searchable press archives across 6 tiers",
        "imageCircleMm": "Web search result / ovide.com: 31.4mm Super 35 diagonal. ManualsLib Angénieux Optimo DP OEM manual (tier-1) + VMI rental hire page / ovide.com (tier-2)",
        "opticalElements": "Not published in Optimo DP documentation",
        "filterType": "ManualsLib OEM manual: internal filter slot only; no front filter thread; filter type uncertain — null",
        "filterThreadMm": "filterType null; internal slot only, no thread size applicable",
        "isParfocal": "Parfocal not explicitly claimed for Optimo DP 30-80mm; POS-D11 applied",
        "hasFocusBreathing": "hhf-old.handheldfilms.com; fjsinternational.com — Zero Breathing and Ramping",
        "hasFrontRotation": "Not stated in accessible documentation",
        "focusRingRotationDeg": "Consistent with Optimo DP 16-42mm OEM manual: 320 degrees. ManualsLib Angénieux Optimo DP OEM manual (tier-1) + VMI rental hire page / ovide.com (tier-2)",
        "gearPitch": "ManualsLib OEM manual: legacy pitch-32 system (25.4/32 = 0.794mm module ≈ 0.8mm) (tier-1)"
      },
      "webSources": [
        "https://www.angenieux.com/cinema-lenses/optimo-dp/"
      ]
    },
    {
      "id": "angenieux-optimo-style-16-40",
      "lensType": "cine",
      "manufacturerUrl": "https://www.angenieux.com/lenses/legacy-series/compact-lens-zoom-optimo-style-16-40/",
      "weightG": 1920,
      "lengthMm": 186,
      "frontDiameterMm": 114,
      "closeFocusM": 0.61,
      "introductionYear": 2014,
      "imageCircleMm": 31.4,
      "opticalElements": null,
      "filterType": "matte_box",
      "filterThreadMm": "none",
      "isParfocal": true,
      "hasFocusBreathing": "minimal",
      "hasFrontRotation": false,
      "focusRingRotationDeg": 320,
      "gearPitch": 0.8,
      "sources": {
        "weightG": "https://www.kinolab.lt/angenieux-optimo-style-16-40mm",
        "lengthMm": "https://www.kinolab.lt/angenieux-optimo-style-16-40mm",
        "frontDiameterMm": "https://www.kinolab.lt/angenieux-optimo-style-16-40mm",
        "closeFocusM": "multiple sources: B&H listing, search results",
        "imageCircleMm": "multiple sources: B&H listing S35+ 31.4mm diagonal",
        "filterType": "search: no filter thread; 114mm front accepts standard matte box clamps",
        "filterThreadMm": "newprovideo.com — Filter Thread: No; angenieux.com",
        "hasFocusBreathing": "search result citing B&H/Newsshooter: 'no signs of breathing during focus pulls'",
        "hasFrontRotation": "search: 'internal focus design, lens length stays constant'",
        "focusRingRotationDeg": "https://www.fdtimes.com/2017/04/20/angenieux-optimo-style-48-130-t3-0/",
        "gearPitch": "https://www.fdtimes.com/2017/04/20/angenieux-optimo-style-48-130-t3-0/",
        "introductionYear": "https://www.topteks.com/nab-2014-angenieux/",
        "isParfocal": "Angénieux Optimo Style datasheet -- angenieux.com (Tier 1)"
      },
      "webSources": [
        "https://www.kinolab.lt/angenieux-optimo-style-16-40mm",
        "https://www.fdtimes.com/2017/04/20/angenieux-optimo-style-48-130-t3-0/",
        "https://www.topteks.com/nab-2014-angenieux/"
      ]
    },
    {
      "id": "angenieux-optimo-style-25-250",
      "lensType": "cine",
      "manufacturerUrl": "https://www.angenieux.com/cinema/optimo-style",
      "weightG": 7200,
      "lengthMm": 377,
      "frontDiameterMm": 136,
      "closeFocusM": 1.22,
      "introductionYear": 2013,
      "imageCircleMm": 31.4,
      "opticalElements": "unknown",
      "filterType": "matte_box",
      "filterThreadMm": "none",
      "isParfocal": true,
      "hasFocusBreathing": "minimal",
      "hasFrontRotation": false,
      "focusRingRotationDeg": 339,
      "gearPitch": 0.8,
      "sources": {
        "introductionYear": "IBC 2013 press release (multiple trade sources)",
        "imageCircleMm": "Angénieux Optimo Style product specifications",
        "weightG": "Duclos Lenses spec database",
        "lengthMm": "Duclos Lenses spec database",
        "frontDiameterMm": "Duclos Lenses spec database",
        "closeFocusM": "Duclos Lenses spec database",
        "filterType": "Angénieux documentation: internal M40.5mm filter slot supplied with lens",
        "filterThreadMm": "angenieux.com — front fitting is for optional protective glass, not a filter thread",
        "hasFrontRotation": "Angénieux documentation: internal focus mechanism confirmed",
        "gearPitch": "Standard M0.8 cinema pitch — rental house documentation",
        "focusRingRotationDeg": "Angénieux Optimo Style 25-250 official user manual (Tier 1): \"Angular rotation of focus ring: 339°/305°\" -- feet scale / metric scale. Using feet scale value.",
        "isParfocal": "Angénieux Optimo Style datasheet -- angenieux.com (Tier 1)"
      },
      "webSources": [
        "https://www.angenieux.com/cinema/optimo-style"
      ]
    },
    {
      "id": "angenieux-optimo-style-30-76",
      "lensType": "cine",
      "manufacturerUrl": "https://www.angenieux.com/lenses/legacy-series/compact-lens-zoom-optimo-style-30-76/",
      "weightG": 1920,
      "lengthMm": 186,
      "frontDiameterMm": 114,
      "closeFocusM": 0.61,
      "introductionYear": 2014,
      "imageCircleMm": 31.4,
      "opticalElements": null,
      "filterType": "matte_box",
      "filterThreadMm": "none",
      "isParfocal": true,
      "hasFocusBreathing": "minimal",
      "hasFrontRotation": false,
      "focusRingRotationDeg": 320,
      "gearPitch": 0.8,
      "sources": {
        "weightG": "multiple sources: 1.92 kg cited in search results",
        "lengthMm": "multiple sources: 186mm cited in search results",
        "frontDiameterMm": "multiple sources: 114mm",
        "closeFocusM": "multiple sources: 2' close focus from B&H listing and search results",
        "imageCircleMm": "search: S35+ 31.4mm diagonal",
        "filterType": "search: no filter thread; 114mm front accepts standard matte box clamps",
        "filterThreadMm": "newprovideo.com; angenieux.com — no filter thread",
        "hasFocusBreathing": "search: 'displaying no signs of breathing during focus pulls'",
        "hasFrontRotation": "search: 'internal focus design, lens length stays constant as focus changes'",
        "focusRingRotationDeg": "https://www.fdtimes.com/2017/04/20/angenieux-optimo-style-48-130-t3-0/",
        "gearPitch": "https://www.fdtimes.com/2017/04/20/angenieux-optimo-style-48-130-t3-0/",
        "introductionYear": "https://www.topteks.com/nab-2014-angenieux/",
        "isParfocal": "Angénieux Optimo Style datasheet -- angenieux.com (Tier 1)"
      },
      "webSources": [
        "https://www.fdtimes.com/2017/04/20/angenieux-optimo-style-48-130-t3-0/",
        "https://www.topteks.com/nab-2014-angenieux/"
      ]
    },
    {
      "id": "angenieux-optimo-style-48-130",
      "lensType": "cine",
      "manufacturerUrl": "https://www.angenieux.com/lenses/legacy-series/optimo-style-48-130/",
      "weightG": 1950,
      "lengthMm": 206,
      "frontDiameterMm": 114,
      "closeFocusM": 0.94,
      "introductionYear": 2017,
      "imageCircleMm": 34.6,
      "opticalElements": null,
      "filterType": "matte_box",
      "filterThreadMm": "none",
      "isParfocal": true,
      "hasFocusBreathing": "minimal",
      "hasFrontRotation": false,
      "focusRingRotationDeg": 320,
      "gearPitch": 0.8,
      "sources": {
        "weightG": "https://www.fdtimes.com/2017/04/20/angenieux-optimo-style-48-130-t3-0/",
        "imageCircleMm": "https://www.fdtimes.com/2017/04/20/angenieux-optimo-style-48-130-t3-0/",
        "hasFocusBreathing": "angenieux.com; fdtimes.com; britishcinematographer.co.uk",
        "filterThreadMm": "angenieux.com; bhphotovideo.com — 114mm front for matte boxes, no filter thread",
        "focusRingRotationDeg": "https://www.fdtimes.com/2017/04/20/angenieux-optimo-style-48-130-t3-0/",
        "gearPitch": "https://www.fdtimes.com/2017/04/20/angenieux-optimo-style-48-130-t3-0/",
        "hasFrontRotation": "https://www.fdtimes.com/2017/04/20/angenieux-optimo-style-48-130-t3-0/",
        "lengthMm": "multiple sources: 206mm from search results",
        "frontDiameterMm": "multiple sources: 114mm from search results",
        "closeFocusM": "multiple sources: 3'1\"/0.94m from search results",
        "introductionYear": "https://www.fdtimes.com/2017/04/20/angenieux-optimo-style-48-130-t3-0/",
        "isParfocal": "Angénieux Optimo Style datasheet -- angenieux.com (Tier 1)"
      },
      "webSources": [
        "https://www.fdtimes.com/2017/04/20/angenieux-optimo-style-48-130-t3-0/"
      ]
    },
    {
      "id": "angenieux-optimo-ultra-12x",
      "lensType": "cine",
      "manufacturerUrl": "https://www.angenieux.com/lenses/optimo-ultra-12x/",
      "weightG": 12247,
      "lengthMm": 472,
      "frontDiameterMm": 162,
      "closeFocusM": 1.22,
      "introductionYear": 2017,
      "imageCircleMm": 31.1,
      "opticalElements": null,
      "filterType": "front_thread",
      "filterThreadMm": 162,
      "isParfocal": true,
      "hasFocusBreathing": "minimal",
      "hasFrontRotation": null,
      "focusRingRotationDeg": 321,
      "gearPitch": 0.8,
      "sources": {
        "weightG": "https://www.ducloslenses.com/products/angenieux-optimo-ultra-12x",
        "lengthMm": "https://www.fdtimes.com/2017/09/04/angenieux-optimo-ultra-12x/",
        "frontDiameterMm": "https://www.fdtimes.com/2017/09/04/angenieux-optimo-ultra-12x/",
        "closeFocusM": "https://www.fdtimes.com/2017/09/04/angenieux-optimo-ultra-12x/",
        "imageCircleMm": "https://www.fdtimes.com/2017/09/04/angenieux-optimo-ultra-12x/",
        "filterThreadMm": "https://www.bandpro.com/angenieux-front-protective-glass-for-12x-optimo-ultra.html",
        "hasFocusBreathing": "Angénieux product sheet Ultra 12x (Tier 1, angenieux.com): 'Low distortion, no ramping, minimal breathing, very fast for 12x zoom ratio.' URL: https://www.angenieux.com/wp-content/uploads/2017/09/Product-sheets-Ultra12x.pdf",
        "focusRingRotationDeg": "https://www.fdtimes.com/2017/09/04/angenieux-optimo-ultra-12x/",
        "gearPitch": "ARRI FF Gear 0.8 Module (K2.0020752) compatibility confirmed via search results",
        "introductionYear": "https://nofilmschool.com/2017/09/angenieux-optimo-ultra-12x-zoom-lens",
        "isParfocal": "Angénieux Optimo Ultra 12x datasheet -- angenieux.com (Tier 1)"
      },
      "webSources": [
        "https://www.ducloslenses.com/products/angenieux-optimo-ultra-12x",
        "https://www.fdtimes.com/2017/09/04/angenieux-optimo-ultra-12x/",
        "https://www.bandpro.com/angenieux-front-protective-glass-for-12x-optimo-ultra.html",
        "https://nofilmschool.com/2017/09/angenieux-optimo-ultra-12x-zoom-lens"
      ]
    },
    {
      "id": "angenieux-optimo-ultra-compact-21-56",
      "lensType": "cine",
      "manufacturerUrl": "https://www.angenieux.com/lenses/optimo-ultra-compact/",
      "weightG": 2800,
      "lengthMm": 235,
      "frontDiameterMm": 114,
      "closeFocusM": 0.61,
      "introductionYear": 2021,
      "imageCircleMm": 46.3,
      "opticalElements": null,
      "filterType": "matte_box",
      "filterThreadMm": "none",
      "isParfocal": true,
      "hasFocusBreathing": "minimal",
      "hasFrontRotation": false,
      "focusRingRotationDeg": 310,
      "gearPitch": 0.8,
      "sources": {
        "weightG": "https://www.bandpro.com/angenieux-optimo-ultra-compact",
        "lengthMm": "https://www.ducloslenses.com/products/ultra2156",
        "frontDiameterMm": "https://www.ducloslenses.com/products/ultra2156",
        "closeFocusM": "https://www.ducloslenses.com/products/ultra2156",
        "imageCircleMm": "https://www.ducloslenses.com/products/ultra2156",
        "hasFocusBreathing": "angenieux.com; bhphotovideo.com; cined.com — no ramping, minimal breathing",
        "hasFrontRotation": "https://www.bandpro.com/angenieux-optimo-ultra-compact",
        "focusRingRotationDeg": "https://www.bandpro.com/angenieux-optimo-ultra-compact",
        "gearPitch": "ARRI FF Gear 0.8 Module compatibility confirmed via search results",
        "introductionYear": "https://www.newsshooter.com/2021/09/23/angenieux-officially-announces-its-37-102mm-t2-9-full-frame-optimo-ultra-compact-zoom/",
        "isParfocal": "Angénieux Ultra Compact portfolio -- angenieux.com (Tier 1)",
        "filterType": "frontDiameterMm=114mm, consistent with all other 114mm Optimo series (Style 16-40/30-76/48-130/15-40/28-76/45-120) which are all matte_box"
      },
      "webSources": [
        "https://www.bandpro.com/angenieux-optimo-ultra-compact",
        "https://www.ducloslenses.com/products/ultra2156",
        "https://www.newsshooter.com/2021/09/23/angenieux-officially-announces-its-37-102mm-t2-9-full-frame-optimo-ultra-compact-zoom/"
      ]
    },
    {
      "id": "angenieux-optimo-ultra-compact-37-102",
      "lensType": "cine",
      "manufacturerUrl": "https://www.angenieux.com/lenses/optimo-ultra-compact/",
      "weightG": 2800,
      "lengthMm": 235,
      "frontDiameterMm": 114,
      "closeFocusM": 0.61,
      "introductionYear": 2021,
      "imageCircleMm": 46.3,
      "opticalElements": null,
      "filterType": "matte_box",
      "filterThreadMm": "none",
      "isParfocal": true,
      "hasFocusBreathing": "minimal",
      "hasFrontRotation": false,
      "focusRingRotationDeg": 310,
      "gearPitch": 0.8,
      "sources": {
        "weightG": "https://www.bandpro.com/angenieux-optimo-ultra-compact",
        "lengthMm": "https://www.ducloslenses.com/products/ultra37102",
        "frontDiameterMm": "https://www.ducloslenses.com/products/ultra37102",
        "closeFocusM": "https://www.ducloslenses.com/products/ultra37102",
        "imageCircleMm": "https://www.ducloslenses.com/products/ultra37102",
        "hasFocusBreathing": "angenieux.com; bhphotovideo.com; fdtimes.com",
        "hasFrontRotation": "https://www.bandpro.com/angenieux-optimo-ultra-compact",
        "focusRingRotationDeg": "https://www.bandpro.com/angenieux-optimo-ultra-compact",
        "gearPitch": "ARRI FF Gear 0.8 Module compatibility confirmed via search results",
        "introductionYear": "https://www.newsshooter.com/2021/09/23/angenieux-officially-announces-its-37-102mm-t2-9-full-frame-optimo-ultra-compact-zoom/",
        "isParfocal": "Angénieux Ultra Compact portfolio -- angenieux.com (Tier 1)",
        "filterType": "frontDiameterMm=114mm, consistent with all other 114mm Optimo series (Style 16-40/30-76/48-130/15-40/28-76/45-120) which are all matte_box"
      },
      "webSources": [
        "https://www.bandpro.com/angenieux-optimo-ultra-compact",
        "https://www.ducloslenses.com/products/ultra37102",
        "https://www.newsshooter.com/2021/09/23/angenieux-officially-announces-its-37-102mm-t2-9-full-frame-optimo-ultra-compact-zoom/"
      ]
    },
    {
      "id": "angenieux-type-ez-1",
      "lensType": "cine",
      "manufacturerUrl": "https://www.angenieux.com/lenses/type-ez-series/",
      "weightG": 2150,
      "lengthMm": 226,
      "frontDiameterMm": 114,
      "closeFocusM": 0.61,
      "introductionYear": 2016,
      "imageCircleMm": 30,
      "opticalElements": null,
      "filterType": "front_thread",
      "filterThreadMm": 110,
      "isParfocal": true,
      "hasFocusBreathing": "minimal",
      "hasFrontRotation": null,
      "focusRingRotationDeg": 300,
      "gearPitch": 0.8,
      "sources": {
        "weightG": "https://www.fdtimes.com/2016/09/06/angenieux-type-ez/",
        "lengthMm": "https://www.ducloslenses.com/products/angenieux-type-ez-1",
        "frontDiameterMm": "https://www.ducloslenses.com/products/angenieux-type-ez-1",
        "closeFocusM": "https://www.ducloslenses.com/products/angenieux-type-ez-1",
        "imageCircleMm": "https://www.ducloslenses.com/products/angenieux-type-ez-1",
        "filterThreadMm": "https://www.ducloslenses.com/products/angenieux-type-ez-1",
        "hasFocusBreathing": "Angénieux EZ Series manual -- angenieux.com (Tier 1)",
        "focusRingRotationDeg": "https://www.fdtimes.com/2016/09/06/angenieux-type-ez/",
        "gearPitch": "multiple sources: EZ series industry-standard 0.8M gears",
        "introductionYear": "https://www.fdtimes.com/2016/09/06/angenieux-type-ez/",
        "isParfocal": "Angénieux EZ Series manual -- angenieux.com (Tier 1)"
      },
      "webSources": [
        "https://www.fdtimes.com/2016/09/06/angenieux-type-ez/",
        "https://www.ducloslenses.com/products/angenieux-type-ez-1"
      ]
    },
    {
      "id": "angenieux-type-ez-2",
      "lensType": "cine",
      "manufacturerUrl": "https://www.angenieux.com/lenses/type-ez-series/",
      "weightG": 2120,
      "lengthMm": 210,
      "frontDiameterMm": 114,
      "closeFocusM": 0.61,
      "introductionYear": 2016,
      "imageCircleMm": 30,
      "opticalElements": null,
      "filterType": "front_thread",
      "filterThreadMm": 110,
      "isParfocal": true,
      "hasFocusBreathing": "minimal",
      "hasFrontRotation": null,
      "focusRingRotationDeg": 300,
      "gearPitch": 0.8,
      "sources": {
        "weightG": "https://www.ducloslenses.com/products/angenieux-type-ez-2-15-40mm-t2-0",
        "lengthMm": "https://www.ducloslenses.com/products/angenieux-type-ez-2-15-40mm-t2-0",
        "frontDiameterMm": "https://www.ducloslenses.com/products/angenieux-type-ez-2-15-40mm-t2-0",
        "closeFocusM": "https://www.ducloslenses.com/products/angenieux-type-ez-2-15-40mm-t2-0",
        "imageCircleMm": "https://www.ducloslenses.com/products/angenieux-type-ez-2-15-40mm-t2-0",
        "filterThreadMm": "https://www.ducloslenses.com/products/angenieux-type-ez-2-15-40mm-t2-0",
        "hasFocusBreathing": "Angénieux EZ Series manual -- angenieux.com (Tier 1)",
        "focusRingRotationDeg": "https://www.fdtimes.com/2016/09/06/angenieux-type-ez/",
        "gearPitch": "multiple sources: EZ series industry-standard 0.8M gears",
        "introductionYear": "https://www.fdtimes.com/2016/09/06/angenieux-type-ez/",
        "isParfocal": "Angénieux EZ Series manual -- angenieux.com (Tier 1)"
      },
      "webSources": [
        "https://www.ducloslenses.com/products/angenieux-type-ez-2-15-40mm-t2-0",
        "https://www.fdtimes.com/2016/09/06/angenieux-type-ez/"
      ]
    },
    {
      "id": "angenieux-type-ez-3",
      "lensType": "cine",
      "manufacturerUrl": "https://www.angenieux.com/lenses/type-ez-series/",
      "weightG": 2600,
      "lengthMm": 264,
      "frontDiameterMm": 114,
      "closeFocusM": 1.22,
      "introductionYear": 2023,
      "imageCircleMm": 30,
      "opticalElements": null,
      "filterType": "front_thread",
      "filterThreadMm": 110,
      "isParfocal": true,
      "hasFocusBreathing": "minimal",
      "hasFrontRotation": null,
      "focusRingRotationDeg": 300,
      "gearPitch": 0.8,
      "sources": {
        "weightG": "multiple sources: 2.6 kg cited in search results for EZ-3 45-165mm",
        "lengthMm": "https://www.ducloslenses.com/products/ez3",
        "frontDiameterMm": "https://www.ducloslenses.com/products/ez3",
        "closeFocusM": "https://www.ducloslenses.com/products/ez3",
        "imageCircleMm": "https://www.ducloslenses.com/products/ez3",
        "filterThreadMm": "https://www.ducloslenses.com/products/ez3",
        "hasFocusBreathing": "Angénieux EZ-3 product brochure -- angenieux.com (Tier 1)",
        "focusRingRotationDeg": "multiple sources: EZ series 300° confirmed across EZ-1/EZ-2/EZ-3",
        "gearPitch": "multiple sources: EZ series industry-standard 0.8M gears",
        "introductionYear": "https://www.newsshooter.com/2023/08/31/angenieux-ez-3-45-163mm-t2-3-3-s35-68-250mm-t3-5-4-ff/",
        "isParfocal": "Angénieux EZ-3 product brochure -- angenieux.com (Tier 1)"
      },
      "webSources": [
        "https://www.ducloslenses.com/products/ez3",
        "https://www.newsshooter.com/2023/08/31/angenieux-ez-3-45-163mm-t2-3-3-s35-68-250mm-t3-5-4-ff/"
      ]
    }
  ]
}
